core_infinity_stones_sso/__init__.py
core_infinity_stones_sso/auth.py
core_infinity_stones_sso/config.py
core_infinity_stones_sso/database.py
core_infinity_stones_sso/dependencies.py
core_infinity_stones_sso/fastapi_integration.py
core_infinity_stones_sso/manager_router.py
core_infinity_stones_sso/models.py
core_infinity_stones_sso/router.py
core_infinity_stones_sso/schemas.py
core_infinity_stones_sso-0.1.2.dist-info/licenses/LICENSE
core_infinity_stones_sso-0.1.2.dist-info/METADATA
core_infinity_stones_sso-0.1.2.dist-info/WHEEL
core_infinity_stones_sso-0.1.2.dist-info/RECORD
