Metadata-Version: 2.4
Name: core-infinity-stones-sso
Version: 0.1.2
Summary: A library for Microsoft SSO authentication and authorization with RBAC support
License: MIT
License-File: LICENSE
Author: Omar Afifi
Requires-Python: >=3.10,<4.0
Classifier: License :: OSI Approved :: MIT License
Classifier: Programming Language :: Python :: 3
Classifier: Programming Language :: Python :: 3.10
Classifier: Programming Language :: Python :: 3.11
Classifier: Programming Language :: Python :: 3.12
Classifier: Programming Language :: Python :: 3.13
Classifier: Programming Language :: Python :: 3.14
Requires-Dist: alembic (>=1.12.1,<2.0.0)
Requires-Dist: fastapi (>=0.103.0,<0.105.0)
Requires-Dist: httpx (==0.25.0)
Requires-Dist: msal (>=1.25.0,<2.0.0)
Requires-Dist: psycopg2-binary (>=2.9.9,<3.0.0)
Requires-Dist: pydantic (>=2.3.0,<3.0.0)
Requires-Dist: pydantic-settings (>=2.0.3,<3.0.0)
Requires-Dist: python-jose[cryptography] (>=3.3.0,<4.0.0)
Requires-Dist: python-multipart (>=0.0.6)
Requires-Dist: sqlalchemy (>=2.0.23,<3.0.0)
Requires-Dist: uvicorn[standard] (>=0.23.0,<0.25.0)
